ecl_data_io/__init__.py
ecl_data_io/array_entry.py
ecl_data_io/errors.py
ecl_data_io/format.py
ecl_data_io/read.py
ecl_data_io/types.py
ecl_data_io/version.py
ecl_data_io/write.py
ecl_data_io/_formatted/__init__.py
ecl_data_io/_formatted/read.py
ecl_data_io/_formatted/write.py
ecl_data_io/_unformatted/__init__.py
ecl_data_io/_unformatted/common.py
ecl_data_io/_unformatted/read.py
ecl_data_io/_unformatted/write.py
ecl_data_io-3.1.3.dist-info/LICENSE.md
ecl_data_io-3.1.3.dist-info/METADATA
ecl_data_io-3.1.3.dist-info/WHEEL
ecl_data_io-3.1.3.dist-info/top_level.txt
ecl_data_io-3.1.3.dist-info/RECORD
