Metadata-Version: 2.1
Name: ecl-data-io
Version: 3.1.3
Summary: A (lazy) parser and writer for the ecl output format.
Author-email: Equinor <fg_sib-scout@equinor.com>
Maintainer-email: Eivind Jahren <ejah@equinor.com>
License: LGPL-3.0
Project-URL: Homepage, https://github.com/equinor/ecl-data-io
Project-URL: Repository, https://github.com/equinor/ecl-data-io
Project-URL: Documentation, https://ecl-data-io.readthedocs.io/en/stable/
Project-URL: Bug Tracker, https://github.com/equinor/ecl-data-io/issues
Classifier: Development Status :: 1 - Planning
Classifier: License :: OSI Approved :: GNU Lesser General Public License v3 or later (LGPLv3+)
Classifier: Programming Language :: Python
Classifier: Programming Language :: Python :: 3.8
Classifier: Programming Language :: Python :: 3.9
Classifier: Programming Language :: Python :: 3.10
License-File: LICENSE.md
Requires-Dist: numpy <2
Provides-Extra: dev
Requires-Dist: pytest ; extra == 'dev'
Requires-Dist: hypothesis ; extra == 'dev'
Requires-Dist: tox ; extra == 'dev'
Requires-Dist: pre-commit ; extra == 'dev'
Provides-Extra: doc
Requires-Dist: sphinx ; extra == 'doc'
Requires-Dist: sphinx-rtd-theme ; extra == 'doc'
